main.py
source_xero/__init__.py
source_xero/components.py
source_xero/manifest.yaml
source_xero/run.py
source_xero/source.py
airbyte_source_xero-2.0.1.dist-info/METADATA
airbyte_source_xero-2.0.1.dist-info/WHEEL
airbyte_source_xero-2.0.1.dist-info/entry_points.txt
airbyte_source_xero-2.0.1.dist-info/RECORD
