Metadata-Version: 2.3
Name: airbyte-source-xero
Version: 2.0.1
Summary: Source implementation for xero.
License: MIT
Author: Airbyte
Author-email: contact@airbyte.io
Requires-Python: >=3.9,<3.12
Classifier: License :: OSI Approved :: MIT License
Classifier: Programming Language :: Python :: 3
Classifier: Programming Language :: Python :: 3.9
Classifier: Programming Language :: Python :: 3.10
Classifier: Programming Language :: Python :: 3.11
Requires-Dist: airbyte-cdk (>=1,<2)
Requires-Dist: pytz
Project-URL: Documentation, https://docs.airbyte.com/integrations/sources/xero
Project-URL: Homepage, https://airbyte.com
Project-URL: Repository, https://github.com/airbytehq/airbyte
